README.rst
setup.py
FormEncode_Jinja2.egg-info/PKG-INFO
FormEncode_Jinja2.egg-info/SOURCES.txt
FormEncode_Jinja2.egg-info/dependency_links.txt
FormEncode_Jinja2.egg-info/requires.txt
FormEncode_Jinja2.egg-info/top_level.txt
FormEncode_Jinja2.egg-info/zip-safe
formencode_jinja2/__init__.py
formencode_jinja2/formfill.py
formencode_jinja2/test_formfill.py