Metadata-Version: 1.1
Name: FormEncode-Jinja2
Version: 0.1.0
Summary: A Jinja2 extension for filling forms via FormEncode
Home-page: https://github.com/Kroisse/FormEncode-Jinja2
Author: Eunchong Yu
Author-email: kroisse@gmail.com
License: MIT License
Keywords: html
Platform: UNKNOWN
Classifier: Development Status :: 4 - Beta
Classifier: Environment :: Web Environment
Classifier: Intended Audience :: Developers
Classifier: License :: OSI Approved :: MIT License
Classifier: Operating System :: OS Independent
Classifier: Programming Language :: Python
Classifier: Programming Language :: Python :: 2 :: Only
Classifier: Programming Language :: Python :: 2.6
Classifier: Programming Language :: Python :: 2.7
Classifier: Programming Language :: Python :: Implementation :: CPython
Classifier: Programming Language :: Python :: Implementation :: PyPy
Classifier: Topic :: Software Development :: Libraries :: Python Modules
